llm_mocks/.DS_Store
llm_mocks/__init__.py
llm_mocks/llm/.DS_Store
llm_mocks/llm/__init__.py
llm_mocks/llm/anthropic/.DS_Store
llm_mocks/llm/anthropic/__init__.py
llm_mocks/llm/anthropic/data/.DS_Store
llm_mocks/llm/anthropic/data/v1_messages.yaml
llm_mocks/llm/anthropic/data/v1_messages_stream.yaml
llm_mocks/llm/base/__init__.py
llm_mocks/llm/cohere/__init__.py
llm_mocks/llm/cohere/data/v1_chat.yaml
llm_mocks/llm/cohere/data/v1_chat_stream.yaml
llm_mocks/llm/cohere/data/v1_embed.yaml
llm_mocks/llm/cohere/data/v1_rerank.yaml
llm_mocks/llm/openai/__init__.py
llm_mocks/llm/openai/data/.DS_Store
llm_mocks/llm/openai/data/v1_chat_completions.yaml
llm_mocks/llm/openai/data/v1_chat_completions_stream.yaml
llm_mocks/llm/openai/data/v1_embeddings.yaml
llm_mocks/llm/openai/data/v1_images_generations.yaml
llm_mocks/utils/__init__.py
llm_mocks/version.py
llm_mocks-0.1.0.dist-info/LICENSE
llm_mocks-0.1.0.dist-info/METADATA
llm_mocks-0.1.0.dist-info/WHEEL
llm_mocks-0.1.0.dist-info/RECORD
