Metadata-Version: 2.1
Name: llm-mocks
Version: 0.1.0
Summary: Mock LLMs' responses for unit-tests
Home-page: https://github.com/AgiFlow/agiflow-sdks
License: MIT
Author: Vuong Ngo
Author-email: vuongngo.pd@gmail.com
Requires-Python: >=3.9,<4
Classifier: License :: OSI Approved :: MIT License
Classifier: Programming Language :: Python :: 3
Classifier: Programming Language :: Python :: 3.9
Classifier: Programming Language :: Python :: 3.10
Classifier: Programming Language :: Python :: 3.11
Classifier: Programming Language :: Python :: 3.12
Requires-Dist: deprecated (>=1.2.14,<2.0.0)
Requires-Dist: wrapt (>=1.16.0,<2.0.0)
Project-URL: Documentation, https://docs.agiflow.io/llm-mocks
Project-URL: Repository, https://github.com/AgiFlow/agiflow-sdks
